[{"class_mtg_info": [{"meet_t": "Mo 7:00PM - 9:30PM", "meet_l": "TBA"}], "school": "SCS", "overview_of_class": "", "qtr": "Winter 2017", "name": "Global Bioethics", "title": "SCS MSGH 419-DL-55 Global Bioethics", "lmod": "2/5/17 6:39 PM (CT)", "section": "55", "instructors": [{"instructor_phone": "312/503-2887", "instructor_name": "Sarah B Rodriguez", "instructor_addr": "Rubloff Building Suite 625, 750 N. Lake Shore, Chicago"}], "topic": "", "course": "419-DL", "enrl_requirement": "", "descriptions": [{"name": "Overview of Class", "value": "Contact the department for further information"}], "path": "/class-descriptions/4650/SCS/MSGH/419-DL/27940", "instructor": ["Sarah B Rodriguez"], "class_attributes": "", "id": "27940", "subject": "MSGH"}]