[{"class_mtg_info": [{"meet_t": "Tu 2:00PM - 5:00PM", "meet_l": "TBA"}], "school": "TGS", "overview_of_class": "", "qtr": "Fall 2017", "name": "Introduction to Social Sciences and Health", "title": "TGS HSIP 430-0-20 Introduction to Social Sciences and Health", "lmod": "9/12/17 6:59 PM (CT)", "section": "20", "topic": "", "course": "430-0", "enrl_requirement": "Enrollment Requirements: Registration is reserved for HSIP Program Students Only<br/>Add Consent: Department Consent Required<br/>", "descriptions": [{"name": "Overview of Class", "value": "Contact the department for further information"}], "instructor": ["Judith Tedlie Moskowitz"], "class_attributes": "", "id": "18468", "subject": "HSIP"}]