[{"class_mtg_info": [{"meet_t": "MoWe 3:30PM - 4:50PM", "meet_l": "University Hall 121"}], "school": "WCAS", "enrl_requirement": "", "qtr": "Winter 2016", "name": "24946", "title": "WCAS HISTORY 357-0-20 East Africa", "class_attributes": "Historical Studies Distro Area<br/><br/>", "section": "24946", "instructors": [{"instructor_phone": "8474917278", "instructor_name": "David Lee   Schoenbrun", "instructor_addr": "Harris Hall Room 303"}], "topic": "", "course": "357-0", "descriptions": [{"name": "Overview of class", "value": "This course will introduce you to the cultural history of eastern Africa, a region that includes today's Kenya, Uganda, Tanzania, Rwanda, Burundi, eastern Democratic Republic of Congo, southern Sudan, southern Ethiopia, and southern Somalia. The course follows chronological developments in two major regions of East Africa: the Great Lakes region and the Indian Ocean coast. No previous knowledge of African history is required. The course will (1) introduce you to non-traditional sources for history?archaeology, environment, historical linguistics, comparative ethnography, and oral traditions?in addition to more conventional textual sources; (2) explore the rise and significance of agriculture in the region; (3) depict the shifting historical relationships between health, wealth, political culture, and social identity; (4) examine the growth of monarchies in many areas of eastern Africa; (5) explore the history of slavery; and (6) engage the cosmopolitan aspirations that tied Eastern Africa to wider worlds."}, {"name": "Teaching Method", "value": "DiscussionLectureLecture with occasional student-led discussion days"}, {"name": "Evaluation Method", "value": "Exam, finalExam, mid-termTake-home midterm, a book review, and a take-home final"}, {"name": "Class Materials (Required)", "value": "Chr\u00e9tien, Great Lakes of Africa ISBN: 978-1890951351<br/><br/><br/>Glassman, Feasts and Riot ISBN: 978-0435089580<br/><br/><br/>Nurse and Spear, The Swahili ISBN: 978-0-8122-1207-5<br/><br/><br/>Schoenbrun, A Green Place ISBN: 978-0325000404<br/><br/><br/>Additional readings posted to Canvas"}, {"name": "Class Notes", "value": "Attendance at first class is mandatory<br/><br/>HISTORY OF CONCENTRATION: Africa"}], "lmod": "1/9/16 6:48 PM (CT)", "subject": "HISTORY"}]