[{"class_mtg_info": [{"meet_t": "We 9:30AM - 12:20PM", "meet_l": "Scott Hall 212"}], "school": "WCAS", "overview_of_class": "", "qtr": "Fall 2017", "name": "Contemporary Theory and Research in Comparative Politics", "title": "WCAS POLI_SCI 450-0-20 Contemporary Theory and Research in Comparative Politics", "lmod": "5/1/17 9:59 AM (CT)", "section": "20", "instructors": [{"instructor_phone": "", "instructor_name": "Andrew L Roberts", "instructor_addr": "Scott, #205"}], "topic": "Proseminar in Comaparative Politics", "course": "450-0", "enrl_requirement": "", "descriptions": [{"name": "Overview of Class", "value": "Contact the department for further information"}], "path": "/class-descriptions/4680/WCAS/POLI_SCI/450-0/13633", "instructor": ["Andrew L Roberts"], "class_attributes": "Graduate Students Only<br/><br/>", "id": "13633", "subject": "POLI_SCI"}]