[{"school": "WCAS", "overview_of_class": "Legal Studies 398-1,2 is a two-quarter sequence required for all Legal Studies majors. This seminar exposes students to a variety of theoretical and methodological approaches to law and legal institutions; over two quarters, students will develop their own research paper on a topic of interest.", "name": "Advanced Research Seminar 1", "section": "20", "topic": "", "course": "398-1", "meeting_time": ["TuTh 11:00AM - 12:20PM"], "path": "/class-descriptions/4640/WCAS/LEGAL_ST/398-1/13156", "instructor": ["Joanna Lynn Grisinger"], "id": "13156", "subject": "LEGAL_ST"}]