[{"class_mtg_info": [{"meet_t": "TuTh 9:30AM - 10:50AM", "meet_l": "Frances Searle Building 3417"}], "school": "SoC", "overview_of_class": "", "qtr": "Fall 2017", "name": "Introduction to Speech, Language, Learning, and Their Disordered", "title": "SoC CSD 320-0-20 Introduction to Speech, Language, Learning, and Their Disordered", "lmod": "5/7/17 10:40 PM (CT)", "section": "20", "topic": "", "course": "320-0", "enrl_requirement": "Enrollment Requirements: Reserved for CSD Undergrads Only", "descriptions": [], "instructor": ["Amy Lynn Mack Sindelar"], "class_attributes": "", "id": "11075", "subject": "CSD"}]