[{"class_mtg_info": [{"meet_t": "TuFr 10:30AM - 12:00PM", "meet_l": "Jacobs Center G05"}], "school": "KGSM", "overview_of_class": "", "qtr": "Spring 2016", "name": "Operations Strategy", "title": "KGSM OPNS 454-0-61 Operations Strategy", "lmod": "4/3/16 6:56 PM (CT)", "section": "61", "instructors": [{"instructor_phone": "", "instructor_name": "Gad   Allon", "instructor_addr": ""}], "topic": "", "course": "454-0", "enrl_requirement": "", "descriptions": [{"name": "Overview of Class", "value": "Contact the department for further information"}], "path": "/class-descriptions/4620/KGSM/OPNS/454-0/30303", "instructor": ["Gad   Allon"], "class_attributes": "Attendance at 1st class mandatory<br/><br/>Elective Course<br/><br/>Open to Exchange Students<br/><br/>", "id": "30303", "subject": "OPNS"}]