[{"school": "WCAS", "overview_of_class": "Development of critical reading and writing skills, literary and historical analysis, philosophy, art history, epigraphy, papyrology, numismatics, and textual criticism. The focus for Spring 2016 is Athens 508-462 BC: the first two generations of the democracy. Readings include Aeschylus' Persians and Suppliant Women. <br/><br/>Required for the major. Pre-requisite: junior or senior standing.", "name": "Research Seminar", "section": "1", "location": "University Hall 112", "topic": "", "course": "395-0", "meeting_time": ["We 3:30PM - 6:20PM"], "path": "/class-descriptions/4620/WCAS/CLASSICS/395-0/37210", "instructor": ["Robert W Wallace"], "class_attributes": "", "id": "37210", "subject": "CLASSICS"}]