[{"class_mtg_info": [{"meet_t": "MoTuWeTh 1:00PM - 1:50PM", "meet_l": "University Library 5746"}], "school": "WCAS", "overview_of_class": "", "qtr": "Fall 2017", "name": "Hebrew II", "title": "WCAS HEBREW 121-1-20 Hebrew II", "lmod": "5/9/17 7:25 PM (CT)", "section": "20", "topic": "", "course": "121-1", "enrl_requirement": "Enrollment Requirements: REASON: Pre-registration is not allowed for this class. Please try again during regular registration.<br/><br/>Pre-requisite: Students must have completed or currently be enrolled in Hebrew 111-3 or an equivalent course.", "descriptions": [{"name": "Overview of Class", "value": "Contact the department for further information"}], "instructor": [""], "class_attributes": "Prerequisites apply, see description<br/><br/>", "id": "12358", "subject": "HEBREW"}]