[{"class_mtg_info": [{"meet_t": "TBA", "meet_l": "TBA"}], "school": "WCAS", "overview_of_class": "", "qtr": "Fall 2017", "name": "TA Assistantship", "title": "WCAS HISTORY 491-0-01 TA Assistantship", "lmod": "5/11/17 7:30 PM (CT)", "section": "01", "topic": "", "course": "491-0", "enrl_requirement": "", "descriptions": [{"name": "Overview of Class", "value": "Contact the department for further information"}], "instructor": ["Kenneth L Alder"], "class_attributes": "", "id": "15249", "subject": "HISTORY"}, {"class_mtg_info": [{"meet_t": "TBA", "meet_l": "TBA"}], "school": "WCAS", "overview_of_class": "", "qtr": "Fall 2017", "name": "TA Assistantship", "title": "WCAS HISTORY 491-0-02 TA Assistantship", "lmod": "5/11/17 7:30 PM (CT)", "section": "02", "topic": "", "course": "491-0", "enrl_requirement": "", "descriptions": [{"name": "Overview of Class", "value": "Contact the department for further information"}], "instructor": ["Michael J. Allen"], "class_attributes": "", "id": "15250", "subject": "HISTORY"}, {"class_mtg_info": [{"meet_t": "TBA", "meet_l": "TBA"}], "school": "WCAS", "overview_of_class": "", "qtr": "Fall 2017", "name": "TA Assistantship", "title": "WCAS HISTORY 491-0-03 TA Assistantship", "lmod": "5/11/17 7:30 PM (CT)", "section": "03", "topic": "", "course": "491-0", "enrl_requirement": "", "descriptions": [{"name": "Overview of Class", "value": "Contact the department for further information"}], "instructor": ["Henry Claxton   Binford"], "class_attributes": "", "id": "15251", "subject": "HISTORY"}, {"class_mtg_info": [{"meet_t": "TBA", "meet_l": "TBA"}], "school": "WCAS", "overview_of_class": "", "qtr": "Fall 2017", "name": "TA Assistantship", "title": "WCAS HISTORY 491-0-04 TA Assistantship", "lmod": "5/11/17 7:30 PM (CT)", "section": "04", "topic": "", "course": "491-0", "enrl_requirement": "", "descriptions": [{"name": "Overview of Class", "value": "Contact the department for further information"}], "instructor": ["Martha   Biondi"], "class_attributes": "", "id": "15252", "subject": "HISTORY"}, {"class_mtg_info": [{"meet_t": "TBA", "meet_l": "TBA"}], "school": "WCAS", "overview_of_class": "", "qtr": "Fall 2017", "name": "TA Assistantship", "title": "WCAS HISTORY 491-0-05 TA Assistantship", "lmod": "5/11/17 7:30 PM (CT)", "section": "05", "topic": "", "course": "491-0", "enrl_requirement": "", "descriptions": [{"name": "Overview of Class", "value": "Contact the department for further information"}], "instructor": ["Caitlin Annette Fitz"], "class_attributes": "", "id": "15253", "subject": "HISTORY"}, {"class_mtg_info": [{"meet_t": "TBA", "meet_l": "TBA"}], "school": "WCAS", "overview_of_class": "", "qtr": "Fall 2017", "name": "TA Assistantship", "title": "WCAS HISTORY 491-0-06 TA Assistantship", "lmod": "5/11/17 7:30 PM (CT)", "section": "06", "topic": "", "course": "491-0", "enrl_requirement": "", "descriptions": [{"name": "Overview of Class", "value": "Contact the department for further information"}], "instructor": ["Rajeev Kumar Kinra"], "class_attributes": "", "id": "15254", "subject": "HISTORY"}, {"class_mtg_info": [{"meet_t": "TBA", "meet_l": "TBA"}], "school": "WCAS", "overview_of_class": "", "qtr": "Fall 2017", "name": "TA Assistantship", "title": "WCAS HISTORY 491-0-08 TA Assistantship", "lmod": "5/11/17 7:30 PM (CT)", "section": "08", "topic": "", "course": "491-0", "enrl_requirement": "", "descriptions": [{"name": "Overview of Class", "value": "Contact the department for further information"}], "instructor": ["John Starkes   Bushnell"], "class_attributes": "", "id": "15255", "subject": "HISTORY"}, {"class_mtg_info": [{"meet_t": "TBA", "meet_l": "TBA"}], "school": "WCAS", "overview_of_class": "", "qtr": "Fall 2017", "name": "TA Assistantship", "title": "WCAS HISTORY 491-0-09 TA Assistantship", "lmod": "5/11/17 7:30 PM (CT)", "section": "09", "topic": "", "course": "491-0", "enrl_requirement": "", "descriptions": [{"name": "Overview of Class", "value": "Contact the department for further information"}], "instructor": ["Peter J Carroll"], "class_attributes": "", "id": "15256", "subject": "HISTORY"}, {"class_mtg_info": [{"meet_t": "TBA", "meet_l": "TBA"}], "school": "WCAS", "overview_of_class": "", "qtr": "Fall 2017", "name": "TA Assistantship", "title": "WCAS HISTORY 491-0-10 TA Assistantship", "lmod": "5/11/17 7:30 PM (CT)", "section": "10", "topic": "", "course": "491-0", "enrl_requirement": "", "descriptions": [{"name": "Overview of Class", "value": "Contact the department for further information"}], "instructor": ["Dyan H Elliott"], "class_attributes": "", "id": "15257", "subject": "HISTORY"}, {"class_mtg_info": [{"meet_t": "TBA", "meet_l": "TBA"}], "school": "WCAS", "overview_of_class": "", "qtr": "Fall 2017", "name": "TA Assistantship", "title": "WCAS HISTORY 491-0-11 TA Assistantship", "lmod": "5/11/17 7:30 PM (CT)", "section": "11", "topic": "", "course": "491-0", "enrl_requirement": "", "descriptions": [{"name": "Overview of Class", "value": "Contact the department for further information"}], "instructor": ["Lane   Fenrich"], "class_attributes": "", "id": "15258", "subject": "HISTORY"}, {"class_mtg_info": [{"meet_t": "TBA", "meet_l": "TBA"}], "school": "WCAS", "overview_of_class": "", "qtr": "Fall 2017", "name": "TA Assistantship", "title": "WCAS HISTORY 491-0-12 TA Assistantship", "lmod": "5/11/17 7:30 PM (CT)", "section": "12", "topic": "", "course": "491-0", "enrl_requirement": "", "descriptions": [{"name": "Overview of Class", "value": "Contact the department for further information"}], "instructor": ["Lydia   Barnett"], "class_attributes": "", "id": "15259", "subject": "HISTORY"}, {"class_mtg_info": [{"meet_t": "TBA", "meet_l": "TBA"}], "school": "WCAS", "overview_of_class": "", "qtr": "Fall 2017", "name": "TA Assistantship", "title": "WCAS HISTORY 491-0-13 TA Assistantship", "lmod": "5/11/17 7:30 PM (CT)", "section": "13", "topic": "", "course": "491-0", "enrl_requirement": "", "descriptions": [{"name": "Overview of Class", "value": "Contact the department for further information"}], "instructor": ["Benjamin   Frommer"], "class_attributes": "", "id": "15260", "subject": "HISTORY"}, {"class_mtg_info": [{"meet_t": "TBA", "meet_l": "TBA"}], "school": "WCAS", "overview_of_class": "", "qtr": "Fall 2017", "name": "TA Assistantship", "title": "WCAS HISTORY 491-0-14 TA Assistantship", "lmod": "5/11/17 7:30 PM (CT)", "section": "14", "topic": "", "course": "491-0", "enrl_requirement": "", "descriptions": [{"name": "Overview of Class", "value": "Contact the department for further information"}], "instructor": ["Jonathon P Glassman"], "class_attributes": "", "id": "15261", "subject": "HISTORY"}, {"class_mtg_info": [{"meet_t": "TBA", "meet_l": "TBA"}], "school": "WCAS", "overview_of_class": "", "qtr": "Fall 2017", "name": "TA Assistantship", "title": "WCAS HISTORY 491-0-15 TA Assistantship", "lmod": "5/11/17 7:30 PM (CT)", "section": "15", "topic": "", "course": "491-0", "enrl_requirement": "", "descriptions": [{"name": "Overview of Class", "value": "Contact the department for further information"}], "instructor": ["Haydon Leslie Cherry"], "class_attributes": "", "id": "15262", "subject": "HISTORY"}, {"class_mtg_info": [{"meet_t": "TBA", "meet_l": "TBA"}], "school": "WCAS", "overview_of_class": "", "qtr": "Fall 2017", "name": "TA Assistantship", "title": "WCAS HISTORY 491-0-16 TA Assistantship", "lmod": "5/11/17 7:30 PM (CT)", "section": "16", "topic": "", "course": "491-0", "enrl_requirement": "", "descriptions": [{"name": "Overview of Class", "value": "Contact the department for further information"}], "instructor": ["Peter Francis   Hayes"], "class_attributes": "", "id": "15263", "subject": "HISTORY"}, {"class_mtg_info": [{"meet_t": "TBA", "meet_l": "TBA"}], "school": "WCAS", "overview_of_class": "", "qtr": "Fall 2017", "name": "TA Assistantship", "title": "WCAS HISTORY 491-0-17 TA Assistantship", "lmod": "5/11/17 7:30 PM (CT)", "section": "17", "topic": "", "course": "491-0", "enrl_requirement": "", "descriptions": [{"name": "Overview of Class", "value": "Contact the department for further information"}], "instructor": ["Laura E Hein"], "class_attributes": "", "id": "15264", "subject": "HISTORY"}, {"class_mtg_info": [{"meet_t": "TBA", "meet_l": "TBA"}], "school": "WCAS", "overview_of_class": "", "qtr": "Fall 2017", "name": "TA Assistantship", "title": "WCAS HISTORY 491-0-18 TA Assistantship", "lmod": "5/11/17 7:30 PM (CT)", "section": "18", "topic": "", "course": "491-0", "enrl_requirement": "", "descriptions": [{"name": "Overview of Class", "value": "Contact the department for further information"}], "instructor": ["Joanna Lynn Grisinger"], "class_attributes": "", "id": "15265", "subject": "HISTORY"}, {"class_mtg_info": [{"meet_t": "TBA", "meet_l": "TBA"}], "school": "WCAS", "overview_of_class": "", "qtr": "Fall 2017", "name": "TA Assistantship", "title": "WCAS HISTORY 491-0-19 TA Assistantship", "lmod": "5/11/17 7:31 PM (CT)", "section": "19", "topic": "", "course": "491-0", "enrl_requirement": "", "descriptions": [{"name": "Overview of Class", "value": "Contact the department for further information"}], "instructor": ["Daniel Sepinuck Immerwahr"], "class_attributes": "", "id": "15266", "subject": "HISTORY"}, {"class_mtg_info": [{"meet_t": "TBA", "meet_l": "TBA"}], "school": "WCAS", "overview_of_class": "", "qtr": "Fall 2017", "name": "TA Assistantship", "title": "WCAS HISTORY 491-0-20 TA Assistantship", "lmod": "5/11/17 7:31 PM (CT)", "section": "20", "topic": "", "course": "491-0", "enrl_requirement": "", "descriptions": [{"name": "Overview of Class", "value": "Contact the department for further information"}], "instructor": ["David   Shyovitz"], "class_attributes": "", "id": "15267", "subject": "HISTORY"}, {"class_mtg_info": [{"meet_t": "TBA", "meet_l": "TBA"}], "school": "WCAS", "overview_of_class": "", "qtr": "Fall 2017", "name": "TA Assistantship", "title": "WCAS HISTORY 491-0-21 TA Assistantship", "lmod": "5/11/17 7:31 PM (CT)", "section": "21", "topic": "", "course": "491-0", "enrl_requirement": "", "descriptions": [{"name": "Overview of Class", "value": "Contact the department for further information"}], "instructor": ["Jacob   Lassner"], "class_attributes": "", "id": "15268", "subject": "HISTORY"}, {"class_mtg_info": [{"meet_t": "TBA", "meet_l": "TBA"}], "school": "WCAS", "overview_of_class": "", "qtr": "Fall 2017", "name": "TA Assistantship", "title": "WCAS HISTORY 491-0-22 TA Assistantship", "lmod": "5/11/17 7:31 PM (CT)", "section": "22", "topic": "", "course": "491-0", "enrl_requirement": "", "descriptions": [{"name": "Overview of Class", "value": "Contact the department for further information"}], "instructor": ["Robert E Lerner"], "class_attributes": "", "id": "15269", "subject": "HISTORY"}, {"class_mtg_info": [{"meet_t": "TBA", "meet_l": "TBA"}], "school": "WCAS", "overview_of_class": "", "qtr": "Fall 2017", "name": "TA Assistantship", "title": "WCAS HISTORY 491-0-23 TA Assistantship", "lmod": "5/11/17 7:31 PM (CT)", "section": "23", "topic": "", "course": "491-0", "enrl_requirement": "", "descriptions": [{"name": "Overview of Class", "value": "Contact the department for further information"}], "instructor": ["Tessie P Liu"], "class_attributes": "", "id": "15270", "subject": "HISTORY"}, {"class_mtg_info": [{"meet_t": "TBA", "meet_l": "TBA"}], "school": "WCAS", "overview_of_class": "", "qtr": "Fall 2017", "name": "TA Assistantship", "title": "WCAS HISTORY 491-0-24 TA Assistantship", "lmod": "5/11/17 7:31 PM (CT)", "section": "24", "topic": "", "course": "491-0", "enrl_requirement": "", "descriptions": [{"name": "Overview of Class", "value": "Contact the department for further information"}], "instructor": ["Melissa A Macauley"], "class_attributes": "", "id": "15271", "subject": "HISTORY"}, {"class_mtg_info": [{"meet_t": "TBA", "meet_l": "TBA"}], "school": "WCAS", "overview_of_class": "", "qtr": "Fall 2017", "name": "TA Assistantship", "title": "WCAS HISTORY 491-0-25 TA Assistantship", "lmod": "5/11/17 7:31 PM (CT)", "section": "25", "topic": "", "course": "491-0", "enrl_requirement": "", "descriptions": [{"name": "Overview of Class", "value": "Contact the department for further information"}], "instructor": ["Deborah Anne Cohen"], "class_attributes": "", "id": "15272", "subject": "HISTORY"}, {"class_mtg_info": [{"meet_t": "TBA", "meet_l": "TBA"}], "school": "WCAS", "overview_of_class": "", "qtr": "Fall 2017", "name": "TA Assistantship", "title": "WCAS HISTORY 491-0-26 TA Assistantship", "lmod": "5/11/17 7:31 PM (CT)", "section": "26", "topic": "", "course": "491-0", "enrl_requirement": "", "descriptions": [{"name": "Overview of Class", "value": "Contact the department for further information"}], "instructor": ["Katherine   Masur"], "class_attributes": "", "id": "15273", "subject": "HISTORY"}, {"class_mtg_info": [{"meet_t": "TBA", "meet_l": "TBA"}], "school": "WCAS", "overview_of_class": "", "qtr": "Fall 2017", "name": "TA Assistantship", "title": "WCAS HISTORY 491-0-27 TA Assistantship", "lmod": "5/11/17 7:31 PM (CT)", "section": "27", "topic": "", "course": "491-0", "enrl_requirement": "", "descriptions": [{"name": "Overview of Class", "value": "Contact the department for further information"}], "instructor": ["Sarah C Maza"], "class_attributes": "", "id": "15274", "subject": "HISTORY"}, {"class_mtg_info": [{"meet_t": "TBA", "meet_l": "TBA"}], "school": "WCAS", "overview_of_class": "", "qtr": "Fall 2017", "name": "TA Assistantship", "title": "WCAS HISTORY 491-0-28 TA Assistantship", "lmod": "5/11/17 7:31 PM (CT)", "section": "28", "topic": "", "course": "491-0", "enrl_requirement": "", "descriptions": [{"name": "Overview of Class", "value": "Contact the department for further information"}], "instructor": ["Rajeev Kumar Kinra"], "class_attributes": "", "id": "15275", "subject": "HISTORY"}, {"class_mtg_info": [{"meet_t": "TBA", "meet_l": "TBA"}], "school": "WCAS", "overview_of_class": "", "qtr": "Fall 2017", "name": "TA Assistantship", "title": "WCAS HISTORY 491-0-29 TA Assistantship", "lmod": "5/11/17 7:31 PM (CT)", "section": "29", "topic": "", "course": "491-0", "enrl_requirement": "", "descriptions": [{"name": "Overview of Class", "value": "Contact the department for further information"}], "instructor": ["Henri   Lauziere"], "class_attributes": "", "id": "15276", "subject": "HISTORY"}, {"class_mtg_info": [{"meet_t": "TBA", "meet_l": "TBA"}], "school": "WCAS", "overview_of_class": "", "qtr": "Fall 2017", "name": "TA Assistantship", "title": "WCAS HISTORY 491-0-30 TA Assistantship", "lmod": "5/11/17 7:31 PM (CT)", "section": "30", "topic": "", "course": "491-0", "enrl_requirement": "", "descriptions": [{"name": "Overview of Class", "value": "Contact the department for further information"}], "instructor": ["Joel   Mokyr"], "class_attributes": "", "id": "15277", "subject": "HISTORY"}, {"class_mtg_info": [{"meet_t": "TBA", "meet_l": "TBA"}], "school": "WCAS", "overview_of_class": "", "qtr": "Fall 2017", "name": "TA Assistantship", "title": "WCAS HISTORY 491-0-31 TA Assistantship", "lmod": "5/11/17 7:31 PM (CT)", "section": "31", "topic": "", "course": "491-0", "enrl_requirement": "", "descriptions": [{"name": "Overview of Class", "value": "Contact the department for further information"}], "instructor": ["Edward Wallace   Muir Jr"], "class_attributes": "", "id": "15278", "subject": "HISTORY"}, {"class_mtg_info": [{"meet_t": "TBA", "meet_l": "TBA"}], "school": "WCAS", "overview_of_class": "", "qtr": "Fall 2017", "name": "TA Assistantship", "title": "WCAS HISTORY 491-0-33 TA Assistantship", "lmod": "5/11/17 7:31 PM (CT)", "section": "33", "topic": "", "course": "491-0", "enrl_requirement": "", "descriptions": [{"name": "Overview of Class", "value": "Contact the department for further information"}], "instructor": ["Kathleen C Belew"], "class_attributes": "", "id": "15279", "subject": "HISTORY"}, {"class_mtg_info": [{"meet_t": "TBA", "meet_l": "TBA"}], "school": "WCAS", "overview_of_class": "", "qtr": "Fall 2017", "name": "TA Assistantship", "title": "WCAS HISTORY 491-0-34 TA Assistantship", "lmod": "5/11/17 7:31 PM (CT)", "section": "34", "topic": "", "course": "491-0", "enrl_requirement": "", "descriptions": [{"name": "Overview of Class", "value": "Contact the department for further information"}], "instructor": ["Susan   Pearson"], "class_attributes": "", "id": "15280", "subject": "HISTORY"}, {"class_mtg_info": [{"meet_t": "TBA", "meet_l": "TBA"}], "school": "WCAS", "overview_of_class": "", "qtr": "Fall 2017", "name": "TA Assistantship", "title": "WCAS HISTORY 491-0-36 TA Assistantship", "lmod": "5/11/17 7:31 PM (CT)", "section": "36", "topic": "", "course": "491-0", "enrl_requirement": "", "descriptions": [{"name": "Overview of Class", "value": "Contact the department for further information"}], "instructor": ["Yohanan   Petrovsky-Shtern"], "class_attributes": "", "id": "15281", "subject": "HISTORY"}, {"class_mtg_info": [{"meet_t": "TBA", "meet_l": "TBA"}], "school": "WCAS", "overview_of_class": "", "qtr": "Fall 2017", "name": "TA Assistantship", "title": "WCAS HISTORY 491-0-37 TA Assistantship", "lmod": "5/11/17 7:31 PM (CT)", "section": "37", "topic": "", "course": "491-0", "enrl_requirement": "", "descriptions": [{"name": "Overview of Class", "value": "Contact the department for further information"}], "instructor": ["Carl Forbes   Petry"], "class_attributes": "", "id": "15282", "subject": "HISTORY"}, {"class_mtg_info": [{"meet_t": "TBA", "meet_l": "TBA"}], "school": "WCAS", "overview_of_class": "", "qtr": "Fall 2017", "name": "TA Assistantship", "title": "WCAS HISTORY 491-0-39 TA Assistantship", "lmod": "5/11/17 7:31 PM (CT)", "section": "39", "topic": "", "course": "491-0", "enrl_requirement": "", "descriptions": [{"name": "Overview of Class", "value": "Contact the department for further information"}], "instructor": ["David   Shyovitz"], "class_attributes": "", "id": "15283", "subject": "HISTORY"}, {"class_mtg_info": [{"meet_t": "TBA", "meet_l": "TBA"}], "school": "WCAS", "overview_of_class": "", "qtr": "Fall 2017", "name": "TA Assistantship", "title": "WCAS HISTORY 491-0-40 TA Assistantship", "lmod": "5/11/17 7:31 PM (CT)", "section": "40", "topic": "", "course": "491-0", "enrl_requirement": "", "descriptions": [{"name": "Overview of Class", "value": "Contact the department for further information"}], "instructor": ["David Lee   Schoenbrun"], "class_attributes": "", "id": "15284", "subject": "HISTORY"}, {"class_mtg_info": [{"meet_t": "TBA", "meet_l": "TBA"}], "school": "WCAS", "overview_of_class": "", "qtr": "Fall 2017", "name": "TA Assistantship", "title": "WCAS HISTORY 491-0-41 TA Assistantship", "lmod": "5/11/17 7:31 PM (CT)", "section": "41", "topic": "", "course": "491-0", "enrl_requirement": "", "descriptions": [{"name": "Overview of Class", "value": "Contact the department for further information"}], "instructor": ["Scott Andrew Sowerby"], "class_attributes": "", "id": "15285", "subject": "HISTORY"}, {"class_mtg_info": [{"meet_t": "TBA", "meet_l": "TBA"}], "school": "WCAS", "overview_of_class": "", "qtr": "Fall 2017", "name": "TA Assistantship", "title": "WCAS HISTORY 491-0-42 TA Assistantship", "lmod": "5/11/17 7:31 PM (CT)", "section": "42", "topic": "", "course": "491-0", "enrl_requirement": "", "descriptions": [{"name": "Overview of Class", "value": "Contact the department for further information"}], "instructor": ["Michael S Sherry"], "class_attributes": "", "id": "15286", "subject": "HISTORY"}, {"class_mtg_info": [{"meet_t": "TBA", "meet_l": "TBA"}], "school": "WCAS", "overview_of_class": "", "qtr": "Fall 2017", "name": "TA Assistantship", "title": "WCAS HISTORY 491-0-43 TA Assistantship", "lmod": "5/11/17 7:31 PM (CT)", "section": "43", "topic": "", "course": "491-0", "enrl_requirement": "", "descriptions": [{"name": "Overview of Class", "value": "Contact the department for further information"}], "instructor": ["Michael J Kramer"], "class_attributes": "", "id": "15287", "subject": "HISTORY"}, {"class_mtg_info": [{"meet_t": "TBA", "meet_l": "TBA"}], "school": "WCAS", "overview_of_class": "", "qtr": "Fall 2017", "name": "TA Assistantship", "title": "WCAS HISTORY 491-0-44 TA Assistantship", "lmod": "5/11/17 7:31 PM (CT)", "section": "44", "topic": "", "course": "491-0", "enrl_requirement": "", "descriptions": [{"name": "Overview of Class", "value": "Contact the department for further information"}], "instructor": ["Helen Louise Tilley"], "class_attributes": "", "id": "15288", "subject": "HISTORY"}, {"class_mtg_info": [{"meet_t": "TBA", "meet_l": "TBA"}], "school": "WCAS", "overview_of_class": "", "qtr": "Fall 2017", "name": "TA Assistantship", "title": "WCAS HISTORY 491-0-45 TA Assistantship", "lmod": "5/11/17 7:31 PM (CT)", "section": "45", "topic": "", "course": "491-0", "enrl_requirement": "", "descriptions": [{"name": "Overview of Class", "value": "Contact the department for further information"}], "instructor": ["Amy Beth Stanley"], "class_attributes": "", "id": "15289", "subject": "HISTORY"}, {"class_mtg_info": [{"meet_t": "TBA", "meet_l": "TBA"}], "school": "WCAS", "overview_of_class": "", "qtr": "Fall 2017", "name": "TA Assistantship", "title": "WCAS HISTORY 491-0-47 TA Assistantship", "lmod": "5/11/17 7:31 PM (CT)", "section": "47", "topic": "", "course": "491-0", "enrl_requirement": "", "descriptions": [{"name": "Overview of Class", "value": "Contact the department for further information"}], "instructor": ["Ji-Yeon   Yuh"], "class_attributes": "", "id": "15290", "subject": "HISTORY"}, {"class_mtg_info": [{"meet_t": "TBA", "meet_l": "TBA"}], "school": "WCAS", "overview_of_class": "", "qtr": "Fall 2017", "name": "TA Assistantship", "title": "WCAS HISTORY 491-0-48 TA Assistantship", "lmod": "5/11/17 7:31 PM (CT)", "section": "48", "topic": "", "course": "491-0", "enrl_requirement": "", "descriptions": [{"name": "Overview of Class", "value": "Contact the department for further information"}], "instructor": ["Geraldo L Cadava"], "class_attributes": "", "id": "15291", "subject": "HISTORY"}, {"class_mtg_info": [{"meet_t": "TBA", "meet_l": "TBA"}], "school": "WCAS", "overview_of_class": "", "qtr": "Fall 2017", "name": "TA Assistantship", "title": "WCAS HISTORY 491-0-49 TA Assistantship", "lmod": "5/11/17 7:31 PM (CT)", "section": "49", "topic": "", "course": "491-0", "enrl_requirement": "", "descriptions": [{"name": "Overview of Class", "value": "Contact the department for further information"}], "instructor": ["Henri   Lauziere"], "class_attributes": "", "id": "15292", "subject": "HISTORY"}, {"class_mtg_info": [{"meet_t": "TBA", "meet_l": "TBA"}], "school": "WCAS", "overview_of_class": "", "qtr": "Fall 2017", "name": "TA Assistantship", "title": "WCAS HISTORY 491-0-50 TA Assistantship", "lmod": "5/11/17 7:31 PM (CT)", "section": "50", "topic": "", "course": "491-0", "enrl_requirement": "", "descriptions": [{"name": "Overview of Class", "value": "Contact the department for further information"}], "instructor": ["Kevin Gerard Boyle"], "class_attributes": "", "id": "15293", "subject": "HISTORY"}, {"class_mtg_info": [{"meet_t": "TBA", "meet_l": "TBA"}], "school": "WCAS", "overview_of_class": "", "qtr": "Fall 2017", "name": "TA Assistantship", "title": "WCAS HISTORY 491-0-51 TA Assistantship", "lmod": "5/11/17 7:31 PM (CT)", "section": "51", "topic": "", "course": "491-0", "enrl_requirement": "", "descriptions": [{"name": "Overview of Class", "value": "Contact the department for further information"}], "instructor": ["Lina M Britto"], "class_attributes": "", "id": "15294", "subject": "HISTORY"}, {"class_mtg_info": [{"meet_t": "TBA", "meet_l": "TBA"}], "school": "WCAS", "overview_of_class": "", "qtr": "Fall 2017", "name": "TA Assistantship", "title": "WCAS HISTORY 491-0-52 TA Assistantship", "lmod": "5/11/17 7:31 PM (CT)", "section": "52", "topic": "", "course": "491-0", "enrl_requirement": "", "descriptions": [{"name": "Overview of Class", "value": "Contact the department for further information"}], "instructor": ["Keith Mako Woodhouse"], "class_attributes": "", "id": "15295", "subject": "HISTORY"}, {"class_mtg_info": [{"meet_t": "TBA", "meet_l": "TBA"}], "school": "WCAS", "overview_of_class": "", "qtr": "Fall 2017", "name": "TA Assistantship", "title": "WCAS HISTORY 491-0-53 TA Assistantship", "lmod": "5/11/17 7:31 PM (CT)", "section": "53", "topic": "", "course": "491-0", "enrl_requirement": "", "descriptions": [{"name": "Overview of Class", "value": "Contact the department for further information"}], "instructor": ["Sean Allen Hanretta"], "class_attributes": "", "id": "15296", "subject": "HISTORY"}, {"class_mtg_info": [{"meet_t": "TBA", "meet_l": "TBA"}], "school": "WCAS", "overview_of_class": "", "qtr": "Fall 2017", "name": "TA Assistantship", "title": "WCAS HISTORY 491-0-54 TA Assistantship", "lmod": "5/11/17 7:31 PM (CT)", "section": "54", "topic": "", "course": "491-0", "enrl_requirement": "", "descriptions": [{"name": "Overview of Class", "value": "Contact the department for further information"}], "instructor": ["Ipek Kocaomer Yosmaoglu"], "class_attributes": "", "id": "15297", "subject": "HISTORY"}, {"class_mtg_info": [{"meet_t": "TBA", "meet_l": "TBA"}], "school": "WCAS", "overview_of_class": "", "qtr": "Fall 2017", "name": "TA Assistantship", "title": "WCAS HISTORY 491-0-55 TA Assistantship", "lmod": "5/11/17 7:31 PM (CT)", "section": "55", "topic": "", "course": "491-0", "enrl_requirement": "", "descriptions": [{"name": "Overview of Class", "value": "Contact the department for further information"}], "instructor": ["Geraldo L Cadava", "Caitlin Annette Fitz"], "class_attributes": "", "id": "15298", "subject": "HISTORY"}, {"class_mtg_info": [{"meet_t": "TBA", "meet_l": "TBA"}], "school": "WCAS", "overview_of_class": "", "qtr": "Fall 2017", "name": "TA Assistantship", "title": "WCAS HISTORY 491-0-56 TA Assistantship", "lmod": "5/11/17 7:31 PM (CT)", "section": "56", "topic": "", "course": "491-0", "enrl_requirement": "", "descriptions": [{"name": "Overview of Class", "value": "Contact the department for further information"}], "instructor": ["Keith Allen Rathbone"], "class_attributes": "", "id": "15299", "subject": "HISTORY"}, {"class_mtg_info": [{"meet_t": "TBA", "meet_l": "TBA"}], "school": "WCAS", "overview_of_class": "", "qtr": "Fall 2017", "name": "TA Assistantship", "title": "WCAS HISTORY 491-0-57 TA Assistantship", "lmod": "5/11/17 7:31 PM (CT)", "section": "57", "topic": "", "course": "491-0", "enrl_requirement": "", "descriptions": [{"name": "Overview of Class", "value": "Contact the department for further information"}], "instructor": ["Daniel A Greene"], "class_attributes": "", "id": "15300", "subject": "HISTORY"}, {"class_mtg_info": [{"meet_t": "TBA", "meet_l": "TBA"}], "school": "WCAS", "overview_of_class": "", "qtr": "Fall 2017", "name": "TA Assistantship", "title": "WCAS HISTORY 491-0-58 TA Assistantship", "lmod": "5/11/17 7:31 PM (CT)", "section": "58", "topic": "", "course": "491-0", "enrl_requirement": "", "descriptions": [{"name": "Overview of Class", "value": "Contact the department for further information"}], "instructor": ["Paul James Gillingham"], "class_attributes": "", "id": "15301", "subject": "HISTORY"}]