[{"class_mtg_info": [{"meet_t": "Th 6:00PM - 9:00PM", "meet_l": "Annenberg Hall 303"}], "school": "SESP", "overview_of_class": "", "qtr": "Fall 2017", "name": "Tools for Organizational Analysis", "title": "SESP LOC 311-0-20 Tools for Organizational Analysis", "lmod": "5/11/17 7:10 PM (CT)", "section": "20", "topic": "", "course": "311-0", "enrl_requirement": "", "descriptions": [{"name": "Overview of Class", "value": "Contact the department for further information"}], "instructor": ["Jeannette A Colyvas"], "class_attributes": "", "id": "14500", "subject": "LOC"}]