[{"school": "MEAS", "overview_of_class": "This course is designed to provide managers with a mix of approaches and techniques to manage technological innovation and change within their organizations. The course is divided into three modules. The first module examines how managers can design teams and organizations to promote innovation. The second module focuses on strategies and structures that encourage and impede effective product development. The third module explores practices that managers can use to implement new technologies and drive organizational change.", "name": "Organizing for Innovation", "section": "1", "location": "Ford Eng Design Cntr ITW 1350", "topic": "", "course": "424-0", "meeting_time": ["Mo 6:00PM - 9:00PM"], "path": "/class-descriptions/4620/MEAS/DSGN/424-0/35104", "instructor": ["Gail Ann Berger"], "class_attributes": "", "id": "35104", "subject": "DSGN"}]