[{"school": "WCAS", "overview_of_class": "This class will involve a close reading of Schiller's _Letters on the Aesthetic Education of Man_ and the first volume of Hegel's _Lectures on Fine Art_. We will focus on two questions. What is the relation between artistic productions and the societies in which they are made? How might aesthetic experience give rise to an experience of transcendence or psychic unity? This class is also designed to introduce students to the basic concepts of Hegelian philosophy.", "name": "Topics in Social and Political Philosophy", "section": "20", "topic": "German Aesthetics: Shiller & Hegel", "course": "361-0", "meeting_time": ["TuTh 12:30PM - 1:50PM"], "path": "/class-descriptions/4650/WCAS/PHIL/361-0/22740", "instructor": ["Mark Vinzenz Alznauer"], "id": "22740", "subject": "PHIL"}, {"school": "WCAS", "overview_of_class": "This class will involve a close reading of Schiller's _Letters on the Aesthetic Education of Man_ and the first volume of Hegel's _Lectures on Fine Art_. We will focus on two questions. What is the relation between artistic productions and the societies in which they are made? How might aesthetic experience give rise to an experience of transcendence or psychic unity? This class is also designed to introduce students to the basic concepts of Hegelian philosophy.", "name": "Topics in Social and Political Philosophy", "section": "21", "topic": "", "course": "361-0", "meeting_time": ["TuTh 12:30PM - 1:50PM"], "path": "/class-descriptions/4650/WCAS/PHIL/361-0/22741", "instructor": ["Mark Vinzenz Alznauer"], "id": "22741", "subject": "PHIL"}]