[{"class_mtg_info": [{"meet_t": "Mo 4:00PM - 5:50PM", "meet_l": "Rubloff Bldg, Rare Book Room"}], "school": "LAW", "enrl_requirement": "Enrollment Requirements: Contracts is a pre-requisite for this course.", "qtr": "Spring 2017", "name": "30353", "title": "LAW BUSCOM 646B-1 International Project Finance", "class_attributes": "Business/Corporate transactions an element<br/><br/>Professional Skills Course<br/><br/>International Law PracticeArea in course<br/><br/>", "section": "30353", "instructors": [{"instructor_phone": "", "instructor_name": "Barry Neil Machlin", "instructor_addr": ""}], "topic": "", "course": "646B", "descriptions": [{"name": "Overview of Class", "value": "Contact the department for further information"}], "lmod": "2/8/17 6:33 PM (CT)", "subject": "BUSCOM"}]