[{"school": "WCAS", "overview_of_class": "While North Africa (the Maghreb) is often considered an appendage of the Muslim Middle East, this Mediterranean region merits study on its own given its French colonial past and its connections to both sub-Saharan Africa and Europe. This course introduces students to the Maghreb through text and expressive culture (film and music).", "name": "Seminar in Middle East and North African Studies", "section": "20", "topic": "Ethnography of North Africa", "course": "301-2", "meeting_time": ["TuTh 9:30AM - 10:50AM"], "path": "/class-descriptions/4610/WCAS/MENA/301-2/23661", "instructor": ["Katherine Elizabeth Hoffman"], "id": "23661", "subject": "MENA"}]