[{"class_mtg_info": [{"meet_t": "Mo 9:00AM - 11:50AM", "meet_l": "Locy Hall 305"}], "school": "SoC", "overview_of_class": "", "qtr": "Fall 2017", "name": "Text Analysis for Theatrical Production", "title": "SoC THEATRE 374-0-20 Text Analysis for Theatrical Production", "lmod": "5/7/17 11:33 PM (CT)", "section": "20", "topic": "", "course": "374-0", "enrl_requirement": "Enrollment Requirements: Registration open to MFA Directing &amp; Design Students Only.<br/>Add Consent: Instructor Consent Required<br/>", "descriptions": [{"name": "Overview of Class", "value": "Contact the department for further information"}], "instructor": ["Kathryn Boehm Walsh"], "class_attributes": "", "id": "14321", "subject": "THEATRE"}]