[{"class_mtg_info": [{"meet_t": "MoWeFr 11:00AM - 11:50AM", "meet_l": "Locy Hall 314"}], "school": "WCAS", "overview_of_class": "For heritage speakers that emphasizes on writing, syntax, and formal modes of the language.", "qtr": "Fall 2017", "name": "Spanish for Heritage Speakers", "title": "WCAS SPANISH 207-0-1 Spanish for Heritage Speakers", "lmod": "5/9/17 7:41 PM (CT)", "section": "1", "topic": "", "course": "207-0", "enrl_requirement": "Enrollment Requirements: REASON: Pre-registration is not allowed for this class. Please try again during regular registration.", "descriptions": [{"name": "Overview of class", "value": "For heritage speakers that emphasizes on writing, syntax, and formal modes of the language."}, {"name": "Registration Requirements", "value": "Three class meetings a week<br/>Prerequisites: 197, AP score of 5 on the Spanish Language or Literature Exam, or departmental Spanish Language Placement Exam<br/>No P/N <br/>Attendance at first class is required."}], "instructor": ["Lidia   Aguilera Lora"], "class_attributes": "", "id": "17331", "subject": "SPANISH"}]