[{"class_mtg_info": [{"meet_t": "TBA", "meet_l": "No Room Needed"}], "school": "MUSIC", "enrl_requirement": "", "qtr": "Spring 2016", "name": "36418", "title": "MUSIC STRINGS 370-0-21 Junior Recital", "class_attributes": "", "section": "36418", "instructors": [{"instructor_phone": "", "instructor_name": "Shmuel   Ashkenasi", "instructor_addr": ""}], "topic": "", "course": "370-0", "descriptions": [{"name": "Overview of Class", "value": "Contact the department for further information"}], "lmod": "4/3/16 6:40 PM (CT)", "subject": "STRINGS"}]