[{"class_mtg_info": [{"meet_t": "TuTh 2:00PM - 3:20PM", "meet_l": "Lunt Hall 101"}], "school": "WCAS", "enrl_requirement": "Enrollment Requirements: PRE-REG:Math Majors Only", "qtr": "Spring 2017", "name": "34209", "title": "WCAS MATH 520-1-81 Topics in Mathematical Physics", "class_attributes": "", "section": "34209", "instructors": [{"instructor_phone": "8474671695", "instructor_name": "Ezra   Getzler", "instructor_addr": "Lunt Hall 308"}], "topic": "", "course": "520-1", "descriptions": [{"name": "Class Materials (Required)", "value": "No Textbook Listed/Needed"}], "lmod": "2/6/17 8:43 AM (CT)", "subject": "MATH"}]