[{"class_mtg_info": [{"meet_t": "Fr 10:00AM - 12:50PM", "meet_l": "McCormick Foundation Ctr 2131"}], "school": "JOUR", "enrl_requirement": "Enrollment Requirements: This section is currently closed to registration.  Please contact the department directly with any questions.<br/>Add Consent: Department Consent Required<br/>", "qtr": "Winter 2017", "name": "23885", "title": "JOUR JOUR 301-0-24 Journalism in Practice", "class_attributes": "Registration is By Application Only<br/><br/>", "section": "23885", "instructors": [{"instructor_phone": "", "instructor_name": "Mei-Ling   Hopgood Reel", "instructor_addr": ""}], "topic": "China", "course": "301-0", "descriptions": [{"name": "Overview of Class", "value": "Contact the department for further information"}], "lmod": "12/24/16 6:44 PM (CT)", "subject": "JOUR"}]