[{"class_mtg_info": [{"meet_t": "MoTuWeThFr 9:00AM - 9:50AM", "meet_l": "Locy Hall 314"}], "school": "WCAS", "enrl_requirement": "", "qtr": "Winter 2016", "name": "23640", "title": "WCAS ARABIC 111-2-20 Arabic I", "class_attributes": "Specific requirements in the language<br/><br/>", "section": "23640", "instructors": [{"instructor_phone": "", "instructor_name": "Amjad M Al-Dajani", "instructor_addr": ""}], "topic": "", "course": "111-2", "descriptions": [{"name": "Overview of class", "value": "<br/>This second course builds upon the material presented in the first term, introducing additional fundamental sentence structures, expanding vocabulary, and providing students an opportunity to further practice and expand the basic skills acquired in the first segment. As with 111-1, students should plan on significant homework outside of class, in addition to the daily class meeting."}, {"name": "Registration Requirements", "value": "<br/>Prerequisite: ARABIC 111-1, or instructor consent"}, {"name": "Class Materials (Required)", "value": "Al-Kitaab fii Tacallum al-cArabiyya<br/>A Textbook for Beginning Arabic: Part One<br/>Third Edition (July 2011)<br/>Kristen Brustad, Mahmoud Al-Batal, and Abbas Al-TonsiGeorgetown University Press<br/>ISBN: 978-1589017368"}], "lmod": "1/9/16 6:43 PM (CT)", "subject": "ARABIC"}]