[{"class_mtg_info": [{"meet_t": "TBA", "meet_l": "TBA"}], "school": "TGS", "enrl_requirement": "<br/>Add Consent: Instructor Consent Required<br/>", "qtr": "Spring 2017", "name": "34620", "title": "TGS PUB_HLTH 435-0-20 Health Services Research Design &amp; Analysis Strategies: Technology Assessment", "class_attributes": "Prerequisites apply, see description<br/><br/>", "section": "34620", "instructors": [{"instructor_phone": "312/503-6443", "instructor_name": "Joseph M Feinglass", "instructor_addr": ""}], "topic": "", "course": "435-0", "descriptions": [{"name": "Overview of Class", "value": "Contact the department for further information"}], "lmod": "2/9/17 6:40 PM (CT)", "subject": "PUB_HLTH"}]