[{"school": "SoC", "overview_of_class": "This seminar will review the new and most recent research literature on how children and adolescents use and are influenced by digital media, especially the newer interactive technologies of tablets, smartphones, interactive toys and the internet.", "name": "Seminar-Problems in Comm Studies", "section": "20", "topic": "Digital Media and Children", "course": "525-0", "meeting_time": ["We 2:00PM - 4:50PM"], "path": "/class-descriptions/4650/SoC/COMM_ST/525-0/23522", "instructor": ["Ellen Ann Wartella"], "id": "23522", "subject": "COMM_ST"}]