[{"class_mtg_info": [{"meet_t": "TBA", "meet_l": "No Room Needed"}], "school": "WCAS", "overview_of_class": "", "qtr": "Summer 2016", "name": "China in Transition: Ideology, Political Economy, Law, and Relations with the US", "title": "WCAS POLI_SCI 379-SA-20 China in Transition: Ideology, Political Economy, Law, and Relations with the US", "lmod": "5/1/16 6:31 PM (CT)", "section": "20", "instructors": [{"instructor_phone": "", "instructor_name": "William James Hurst", "instructor_addr": ""}], "topic": "", "course": "379-SA", "enrl_requirement": "<br/>Add Consent: Department Consent Required<br/>", "descriptions": [{"name": "Overview of Class", "value": "Contact the department for further information"}], "path": "/class-descriptions/4630/WCAS/POLI_SCI/379-SA/41873", "instructor": ["William James Hurst"], "class_attributes": "Social &amp; Behavioral Sciences Distro Area<br/><br/>", "id": "41873", "subject": "POLI_SCI"}]