[{"class_mtg_info": [{"meet_t": "Tu 2:00PM - 4:50PM", "meet_l": "Kresge 3364 Slavic Seminar Rm"}], "school": "WCAS", "overview_of_class": "This course offers a survey of Russian 18th-century culture in its major literary genres and generic trends, that is, classicism in its fictional and poetic polarities. Moreover, students will be introduced to European classicism in literature as some bigger screen to project and compare with the Russian one. Students are expected to learn about their major theoretical and practical similarities as well as differences. A focus of this course is works by Lomonosov,Trediakovsky, Sumarokov, Derzhavin, Bogdanovich, Knyazhnin, Fonvizin, and Karamzin, in comparison with Dryden and Pope (England), Boileau, Racine and Corneille (France). Students will also become acquainted with classicist visual art.", "qtr": "Fall 2016", "name": "Studies in 18Th Century Russian Lit", "title": "WCAS SLAVIC 434-0-1 Studies in 18Th Century Russian Lit", "lmod": "10/30/16 7:10 PM (CT)", "section": "1", "instructors": [{"instructor_phone": "", "instructor_name": "Ilya   Kutik", "instructor_addr": "1880 Campus Dr. (Kresge) Office 3363"}], "topic": "", "course": "434-0", "enrl_requirement": "", "descriptions": [{"name": "Overview of class", "value": "This course offers a survey of Russian 18th-century culture in its major literary genres and generic trends, that is, classicism in its fictional and poetic polarities. Moreover, students will be introduced to European classicism in literature as some bigger screen to project and compare with the Russian one. Students are expected to learn about their major theoretical and practical similarities as well as differences. A focus of this course is works by Lomonosov,Trediakovsky, Sumarokov, Derzhavin, Bogdanovich, Knyazhnin, Fonvizin, and Karamzin, in comparison with Dryden and Pope (England), Boileau, Racine and Corneille (France). Students will also become acquainted with classicist visual art."}, {"name": "Teaching Method", "value": "Lecture and Discussion"}, {"name": "Evaluation Method", "value": "Evaluation is based on weekly presentations, in-class participation, and final paper."}], "path": "/class-descriptions/4640/WCAS/SLAVIC/434-0/14376", "instructor": ["Ilya   Kutik"], "class_attributes": "", "id": "14376", "subject": "SLAVIC"}]