[{"class_mtg_info": [{"meet_t": "TBA", "meet_l": "TBA"}], "school": "TGS", "overview_of_class": "", "qtr": "Fall 2017", "name": "Advanced Qualitative Methods & Analysis for Health Researchers", "title": "TGS HSR 480-0-1 Advanced Qualitative Methods &amp; Analysis for Health Researchers", "lmod": "5/11/17 7:14 PM (CT)", "section": "1", "topic": "", "course": "480-0", "enrl_requirement": "<br/>Add Consent: Department Consent Required<br/>", "descriptions": [{"name": "Overview of Class", "value": "Contact the department for further information"}], "instructor": ["Elisa J Gordon"], "class_attributes": "", "id": "16546", "subject": "HSR"}]