[{"class_mtg_info": [{"meet_t": "Mo 6:00PM - 7:50PM", "meet_l": "Rubloff Building 256"}], "school": "LAW", "enrl_requirement": "", "qtr": "Spring 2017", "name": "30299", "title": "LAW LITARB 600-1 Legal Ethics", "class_attributes": "Meets Legal Ethics degree requirement<br/><br/>Civil Litigation &amp; Dispute Resolution<br/><br/>", "section": "30299", "instructors": [{"instructor_phone": "", "instructor_name": "Adam Lawrence Hoeflich", "instructor_addr": ""}], "topic": "", "course": "600", "descriptions": [{"name": "Overview of Class", "value": "Contact the department for further information"}], "lmod": "2/8/17 6:33 PM (CT)", "subject": "LITARB"}]