[{"school": "SCS", "overview_of_class": "Corporate Finance 360 will give the student a good overview of the world of Capital Markets including the role of the corporation in society,the  concept and definition of risk and reward, size and valuation of the fixed income and equity markets, the definition of derivatives and some trading strategies, balance sheet analysis, project finance, corporate valuation, the investment banking process and corporate bankruptcies and trading of distressed debt.   <br/><br/>Course Overview guidelines:<br/><br/>? Definition and significance of capital markets<br/>? Definition of risk and reward and quantification of risk<br/>? Overview of the fixed income market and specific valuation methods<br/>? Various ways to classify equities as well as valuation techniques<br/>? Corporate Valuation and Project Finance methodologies<br/>? The role of an investment banker and banking process as well and bankruptcies.", "name": "Corporate Finance", "section": "62", "topic": "", "course": "360-CN", "meeting_time": ["Mo 6:15PM - 9:15PM"], "path": "/class-descriptions/4610/SCS/FINANCE/360-CN/27780", "instructor": ["David D Walker"], "id": "27780", "subject": "FINANCE"}]